<?xml version="1.0" encoding="UTF-8"?>
<Tokens version="1.0">
	<File path="Protocols/SnSCacheConnectionHandler.html">
		
		<Token>
			<TokenIdentifier>//apple_ref/occ/intf/SnSCacheConnectionHandler</TokenIdentifier>
			<Abstract></Abstract>
			<DeclaredIn>SnSCacheDelegate.h</DeclaredIn>
			
			<NodeRef refid="67"/>
		</Token>
		
		
		<Token>
			<TokenIdentifier>//apple_ref/occ/intfm/SnSCacheConnectionHandler/handleSynchronousURLConnection:returningResponse:error:</TokenIdentifier>
			<Abstract></Abstract>
			<DeclaredIn>SnSCacheDelegate.h</DeclaredIn>			
			
			<Declaration>- (NSData *)handleSynchronousURLConnection:(NSURLRequest *)iRequest returningResponse:(NSURLResponse **)oResponse error:(NSError **)oError</Declaration>
			
			
			<Anchor>//api/name/handleSynchronousURLConnection:returningResponse:error:</Anchor>
		</Token>
		
	</File>
</Tokens>